whatapackage/__init__.py
whatapackage/hey.py
whatapackage-0.0.8.dist-info/METADATA
whatapackage-0.0.8.dist-info/WHEEL
whatapackage-0.0.8.dist-info/top_level.txt
whatapackage-0.0.8.dist-info/RECORD
